ipv6.cpython-38-x86_64-linux-gnu.so
ipv6-1.23.dist-info/METADATA
ipv6-1.23.dist-info/WHEEL
ipv6-1.23.dist-info/top_level.txt
ipv6-1.23.dist-info/LICENSE
ipv6-1.23.dist-info/RECORD
