Metadata-Version: 2.1
Name: ipv6
Version: 1.23
Summary: Advanced IPv6 Socket Manipulation for Python
Home-page: https://github.com/nasa/ipv6_python
Author: Joseph Ishac
Author-email: jishac@nasa.gov
License: NASA Open Source Agreement version 1.3
Platform: UNKNOWN
